{
"type": "FeatureCollection",
"name": "hypo_landmarks",
"crs": { "type": "name", "properties": { "name": "urn:ogc:def:crs:OGC:1.3:CRS84" } },
"features": [
{ "type": "Feature", "properties": { "id": 1 }, "geometry": { "type": "Point", "coordinates": [ 144.988428775565069, -37.81803217109843 ] } },
{ "type": "Feature", "properties": { "id": 2 }, "geometry": { "type": "Point", "coordinates": [ 144.995277597198594, -37.816229849615922 ] } },
{ "type": "Feature", "properties": { "id": 3 }, "geometry": { "type": "Point", "coordinates": [ 144.988428775565069, -37.814427528133407 ] } },
{ "type": "Feature", "properties": { "id": 4 }, "geometry": { "type": "Point", "coordinates": [ 144.981579953931515, -37.816229849615922 ] } },
{ "type": "Feature", "properties": { "id": 5 }, "geometry": { "type": "Point", "coordinates": [ 144.975091596594467, -37.821312396196603 ] } },
{ "type": "Feature", "properties": { "id": 6 }, "geometry": { "type": "Point", "coordinates": [ 144.970802071466096, -37.822429835515763 ] } },
{ "type": "Feature", "properties": { "id": 7 }, "geometry": { "type": "Point", "coordinates": [ 144.966512546337697, -37.821312396196603 ] } },
{ "type": "Feature", "properties": { "id": 8 }, "geometry": { "type": "Point", "coordinates": [ 144.970802071466096, -37.820194956877444 ] } },
{ "type": "Feature", "properties": { "id": 9 }, "geometry": { "type": "Point", "coordinates": [ 144.970621839317829, -37.826322849917986 ] } },
{ "type": "Feature", "properties": { "id": 10 }, "geometry": { "type": "Point", "coordinates": [ 144.974659039438649, -37.828701914274902 ] } },
{ "type": "Feature", "properties": { "id": 11 }, "geometry": { "type": "Point", "coordinates": [ 144.970621839317829, -37.831080978631825 ] } },
{ "type": "Feature", "properties": { "id": 12 }, "geometry": { "type": "Point", "coordinates": [ 144.966584639197009, -37.828701914274902 ] } },
{ "type": "Feature", "properties": { "id": 13 }, "geometry": { "type": "Point", "coordinates": [ 145.009768261917998, -37.821564721204155 ] } },
{ "type": "Feature", "properties": { "id": 14 }, "geometry": { "type": "Point", "coordinates": [ 145.013733369179533, -37.82646703563659 ] } },
{ "type": "Feature", "properties": { "id": 15 }, "geometry": { "type": "Point", "coordinates": [ 145.009768261917998, -37.831369350069025 ] } },
{ "type": "Feature", "properties": { "id": 16 }, "geometry": { "type": "Point", "coordinates": [ 145.005803154656462, -37.82646703563659 ] } },
{ "type": "Feature", "properties": { "id": 17 }, "geometry": { "type": "Point", "coordinates": [ 145.007754167661233, -37.81533178661472 ] } },
{ "type": "Feature", "properties": { "id": 18 }, "geometry": { "type": "Point", "coordinates": [ 144.981296088295636, -37.801345771910427 ] } },
{ "type": "Feature", "properties": { "id": 19 }, "geometry": { "type": "Point", "coordinates": [ 144.980254121191166, -37.809037742060305 ] } },
{ "type": "Feature", "properties": { "id": 20 }, "geometry": { "type": "Point", "coordinates": [ 144.974082296564262, -37.803938017105182 ] } },
{ "type": "Feature", "properties": { "id": 21 }, "geometry": { "type": "Point", "coordinates": [ 144.971234628621886, -37.802604299208127 ] } },
{ "type": "Feature", "properties": { "id": 22 }, "geometry": { "type": "Point", "coordinates": [ 144.971234628621886, -37.805271735002243 ] } },
{ "type": "Feature", "properties": { "id": 23 }, "geometry": { "type": "Point", "coordinates": [ 144.96838696067951, -37.803938017105182 ] } },
{ "type": "Feature", "properties": { "id": 24 }, "geometry": { "type": "Point", "coordinates": [ 144.995714660157006, -37.821027122499459 ] } },
{ "type": "Feature", "properties": { "id": 25 }, "geometry": { "type": "Point", "coordinates": [ 144.979677378316751, -37.827853978339384 ] } },
{ "type": "Feature", "properties": { "id": 26 }, "geometry": { "type": "Point", "coordinates": [ 144.983098409778307, -37.821027122499459 ] } },
{ "type": "Feature", "properties": { "id": 27 }, "geometry": { "type": "Point", "coordinates": [ 144.962951834959057, -37.820500506690088 ] } },
{ "type": "Feature", "properties": { "id": 28 }, "geometry": { "type": "Point", "coordinates": [ 145.013809967843002, -37.81533178661472 ] } }
]
}
